mbodied_agents/__about__.py
mbodied_agents/__init__.py
mbodied_agents/agents/__init__.py
mbodied_agents/agents/backends/__init__.py
mbodied_agents/agents/backends/anthropic_backend.py
mbodied_agents/agents/backends/huggingface_backend.py
mbodied_agents/agents/backends/mbodi_backend.py
mbodied_agents/agents/backends/ollama_backend.py
mbodied_agents/agents/backends/openai_backend.py
mbodied_agents/agents/language/__init__.py
mbodied_agents/agents/language/language_agent.py
mbodied_agents/agents/motion/__init__.py
mbodied_agents/agents/motion/motor_agent.py
mbodied_agents/agents/motion/openvla_agent.py
mbodied_agents/agents/motion/openvla_example_server.py
mbodied_agents/agents/sense/__init__.py
mbodied_agents/agents/sense/audio/audio_handler.py
mbodied_agents/base/__init__.py
mbodied_agents/base/agent.py
mbodied_agents/base/backend.py
mbodied_agents/base/motion.py
mbodied_agents/base/sample.py
mbodied_agents/base/serializer.py
mbodied_agents/data/__init__.py
mbodied_agents/data/recording.py
mbodied_agents/data/replaying.py
mbodied_agents/data/utils.py
mbodied_agents/hardware/__init__.py
mbodied_agents/hardware/interface.py
mbodied_agents/hardware/remote_interface.py
mbodied_agents/hardware/sim_interface.py
mbodied_agents/hardware/xarm_interface.py
mbodied_agents/types/__init__.py
mbodied_agents/types/controls.py
mbodied_agents/types/geometry.py
mbodied_agents/types/language_controls.py
mbodied_agents/types/message.py
mbodied_agents/types/ndarray.py
mbodied_agents/types/sense/__init__.py
mbodied_agents/types/sense/depth.py
mbodied_agents/types/sense/vision.py
mbodied_agents/resources/locobot.jpeg
mbodied_agents/resources/xarm.jpeg
mbodied_agents-0.0.7.dist-info/METADATA
mbodied_agents-0.0.7.dist-info/WHEEL
mbodied_agents-0.0.7.dist-info/licenses/LICENSE
mbodied_agents-0.0.7.dist-info/RECORD
