Metadata-Version: 2.3
Name: mbodied-agents
Version: 0.0.7
Summary: Embodied AI
Project-URL: Documentation, https://github.com/mbodiai/mbodied-agents#readme
Project-URL: Issues, https://github.com/mbodiai/mbodied-agents/issues
Project-URL: Source, https://github.com/mbodiai/mbodied-agents
Author-email: Mbodi Team <info@mbodi.ai>
License-Expression: Apache-2.0
License-File: LICENSE
Classifier: Development Status :: 4 - Beta
Classifier: Programming Language :: Python
Classifier: Programming Language :: Python :: 3.11
Classifier: Programming Language :: Python :: Implementation :: CPython
Classifier: Programming Language :: Python :: Implementation :: PyPy
Requires-Python: <=3.13,>=3.10
Requires-Dist: anthropic
Requires-Dist: art
Requires-Dist: backoff
Requires-Dist: click
Requires-Dist: coverage[toml]
Requires-Dist: datasets
Requires-Dist: gradio
Requires-Dist: gradio-client
Requires-Dist: gymnasium
Requires-Dist: h5py
Requires-Dist: jsonref
Requires-Dist: numpy==1.26.4
Requires-Dist: openai
Requires-Dist: opencv-python
Requires-Dist: pillow
Requires-Dist: pydantic
Requires-Dist: pydantic-numpy==5.0.2
Requires-Dist: pytest
Requires-Dist: pytest-mock
Requires-Dist: toml
Requires-Dist: torch
Requires-Dist: transformers
Requires-Dist: xarm-python-sdk
Provides-Extra: all
Requires-Dist: open3d; extra == 'all'
Requires-Dist: playsound; extra == 'all'
Requires-Dist: pyaudio; extra == 'all'
Provides-Extra: extras
Requires-Dist: playsound; extra == 'extras'
Requires-Dist: pyaudio; extra == 'extras'
